MANIFEST.in
README.md
config.json
setup.py
bib_extractor/__init__.py
bib_extractor/bib_extractor_cli.py
bib_extractor/bib_extractor_main.py
bib_extractor/core_modules.py
bib_extractor/merge_parsers.py
bib_extractor/multiprocess.py
bib_extractor/system_loader.py
bib_extractor.egg-info/PKG-INFO
bib_extractor.egg-info/SOURCES.txt
bib_extractor.egg-info/dependency_links.txt
bib_extractor.egg-info/entry_points.txt
bib_extractor.egg-info/top_level.txt
test/__init__.py
test/input_test1.json
test/input_test2.json
test/input_test3.json
test/input_test4.json
test/test_list_bib_refs.json
test/test_modules.py
test/test_parser_bibref2meta.json
test/texts_list.txt
test/texts/text1.txt
test/texts/text2.txt
test/texts/text3.txt