Metadata-Version: 1.0
Name: bib-extractor
Version: 0.0.2
Summary: Extraction references and check their style
Home-page: UNKNOWN
Author: dpopov
Author-email: dpopov@tesyan.ru
License: UNKNOWN
Platform: UNKNOWN
